cedarpy_conversor-0.0.2.dist-info/METADATA
cedarpy_conversor-0.0.2.dist-info/WHEEL
cedarpy_conversor-0.0.2.dist-info/license_files/LICENSE
cedarpy_conversor/__init__.py
cedarpy_conversor/cedarpy_conversor.pyi
cedarpy_conversor/py.typed
cedarpy_conversor/_internal.cpython-39-darwin.so
cedarpy_conversor-0.0.2.dist-info/RECORD
