Metadata-Version: 2.1
Name: cedarpy_conversor
Version: 0.0.2
Classifier: Programming Language :: Rust
Classifier: Programming Language :: Python :: Implementation :: CPython
Classifier: Programming Language :: Python :: Implementation :: PyPy
Requires-Dist: maturin ==1.1.0 ; extra == 'dev'
Requires-Dist: parameterized ==0.9.0 ; extra == 'dev'
Requires-Dist: pip-tools ==6.13.0 ; extra == 'dev'
Requires-Dist: pytest ==7.4.0 ; extra == 'dev'
Provides-Extra: dev
License-File: LICENSE
Requires-Python: >=3.9
